FULL_SUBTRACTOR/design.sv
// Code your design here
module Full_Subtractor(output D, B, input X, Y, Z);
  assign D = X ^ Y ^ Z;
  assign B = ~X & (Y^Z) | Y & Z;
endmodule

FULL_SUBTRACTOR/testbench.sv
// Code your testbench here
// or browse Examples
`timescale 1ns/1ns
module Full_Subtractor_tb;
  wire D, B;
  reg X, Y, Z;
  Full_Subtractor UUT (D, B, X, Y, Z);
  initial begin
    X = 0; Y = 0; Z = 0;
    #1  X = 0; Y = 0; Z = 1;
    #1  X = 0; Y = 1; Z = 0;
    #1  X = 0; Y = 1; Z = 1;
    #1  X = 1; Y = 0; Z = 0;
    #1  X = 1; Y = 0; Z = 1;
    #1  X = 1; Y = 1; Z = 0;
    #1  X = 1; Y = 1; Z = 1; 
  end
  initial begin
    $monitor ("%t, X = %d| Y = %d| Z = %d| B = %d| D = %d", $time, X, Y, Z, B, D);
    $dumpfile("dump.vcd");
    $dumpvars();
  end
endmodule

FULL_SUBTRACTOR/dump.vcd
$date
	Sat May 15 10:15:35 2021
$end
$version
	Icarus Verilog
$end
$timescale
	1ns
$end
$scope module Full_Subtractor_tb $end
$var wire 1 ! D $end
$var wire 1 " B $end
$var reg 1 # X $end
$var reg 1 $ Y $end
$var reg 1 % Z $end
$scope module UUT $end
$var wire 1 " B $end
$var wire 1 ! D $end
$var wire 1 # X $end
$var wire 1 $ Y $end
$var wire 1 % Z $end
$upscope $end
$upscope $end
$enddefinitions $end
#0
$dumpvars
0%
0$
0#
0"
0!
$end
#1
1"
1!
1%
#2
0%
1$
#3
0!
1%
#4
0"
1!
0%
0$
1#
#5
0!
1%
#6
0%
1$
#7
1"
1!
1%
