JK_FF/design.sv
// Code your design here
module jk_ff(input j, input k, input clk, output reg q);
  always @ (posedge clk)
    begin
      case ({j,k})
        2'b00: q = q;
        2'b01: q = 0;
        2'b10: q = 1;
        2'b11: q = ~q;
      endcase
    end
endmodule

JK_FF/testbench.sv
// Code your testbench here
// or browse Examples
module jk_ff_tb();
  reg j,k,clk;
  wire q;
  jk_ff UUT (j,k,clk,q);
  initial begin
    j <= 0; k <= 0;
    #2 clk <=0;
  end
  always #5 clk = ~clk;
  initial begin
    $dumpfile("dump.vcd");
    $dumpvars;
    $monitor("%d %d -> %d", j,k,q);
    #25 j <= 0; k <= 1;
    #25 j <= 0; k <= 0;
    #25 j <= 1; k <= 0;
    #25 j <= 0; k <= 0;
    #25 j <= 0; k <= 1;
    #500 $finish;
  end
endmodule

JK_FF/dump.vcd
$date
	Fri May 14 17:56:37 2021
$end
$version
	Icarus Verilog
$end
$timescale
	1s
$end
$scope module jk_ff_tb $end
$var wire 1 ! q $end
$var reg 1 " clk $end
$var reg 1 # j $end
$var reg 1 $ k $end
$scope module UUT $end
$var wire 1 " clk $end
$var wire 1 # j $end
$var wire 1 $ k $end
$var reg 1 ! q $end
$upscope $end
$upscope $end
$enddefinitions $end
#0
$dumpvars
0$
0#
x"
x!
$end
#2
0"
#5
1"
#10
0"
#15
1"
#20
0"
#25
1$
1"
#30
0"
#35
0!
1"
#40
0"
#45
1"
#50
0$
0"
#55
1"
#60
0"
#65
1"
#70
0"
#75
1#
1"
#80
0"
#85
1!
1"
#90
0"
#95
1"
#100
0#
0"
#105
1"
#110
0"
#115
1"
#120
0"
#125
1$
1"
#130
0"
#135
0!
1"
