SR_FF/design.sv
module rs_flipflop(input a, input b, input clk, output q);
  reg q;
  always@(posedge clk)
    case({a,b})
      2'b00 : q = q;
      2'b01 : q = 0;
      2'b10 : q = 1;
      2'b11 : q = ~q;
    endcase
endmodule

SR_FF/testbench.sv
module rs_flipflop_tb();
  wire q;
  reg a,b,clk;
  rs_flipflop UUT(.q(q),.a(a),.b(b),.clk(clk));
  initial begin
    a=0;b=0; #2 clk=0;
  end
  always 
    #25 clk = ~clk;
  initial begin
    $dumpfile("rsfp.vcd");
    $dumpvars;
    #25 a=0; b=1;
	#25 a=0; b=0;
	#25 a=1; b=0;
	#25 a=0; b=0;
	#25 a=0; b=1;
    #25 a=1; b=0;
	#250 $finish;
  end
endmodule

SR_FF/rsfp.vcd
$date
	Fri May 14 08:17:11 2021
$end
$version
	Icarus Verilog
$end
$timescale
	1s
$end
$scope module rs_flipflop_tb $end
$var wire 1 ! q $end
$var reg 1 " a $end
$var reg 1 # b $end
$var reg 1 $ clk $end
$scope module UUT $end
$var wire 1 " a $end
$var wire 1 # b $end
$var wire 1 $ clk $end
$var reg 1 ! q $end
$upscope $end
$upscope $end
$enddefinitions $end
#0
$dumpvars
x$
0#
0"
x!
$end
#2
0$
#25
0!
1#
1$
#50
0#
0$
#75
1!
1"
1$
#100
0"
0$
#125
0!
1#
1$
#150
0#
1"
0$
#175
1!
1$
